aldict-1.1.2.dist-info/METADATA
aldict-1.1.2.dist-info/WHEEL
aldict-1.1.2.dist-info/entry_points.txt
aldict-1.1.2.dist-info/licenses/LICENSE
aldict/__init__.py
aldict/alias_dict.py
aldict/exception.py
aldict-1.1.2.dist-info/RECORD
