Metadata-Version: 2.4
Name: aldict
Version: 1.1.2
Summary: Multi-key dictionary, supports adding and manipulating key-aliases pointing to shared values
Keywords: multi-key dictionary,multidict,alias-dict
Author-Email: kaliv0 <kaloyan.ivanov88@gmail.com>
License-File: LICENSE
Project-URL: repository, https://github.com/kaliv0/aldict
Requires-Python: >=3.10
